{"cameraMode":{"drawMode":0,"name":"Shaded","section":"Shading Mode"},"sceneLighting":false,"audioPlay":false,"sceneViewState":{"showFog":true,"showMaterialUpdate":false,"showSkybox":false,"showFlares":true,"showImageEffects":true,"showParticleSystems":true,"showVisualEffectGraphs":true,"m_FxEnabled":true},"in2DMode":false,"pivot":{"x":-117.73202514648438,"y":-85.23090362548828,"z":130.56394958496095},"rotation":{"x":-0.028191711753606797,"y":0.9717927575111389,"z":-0.17774984240531922,"w":-0.154561385512352},"size":9.359352111816407,"orthographic":false}