{"cameraMode":{"drawMode":0,"name":"Shaded","section":"Shading Mode"},"sceneLighting":true,"audioPlay":false,"sceneViewState":{"showFog":true,"showMaterialUpdate":false,"showSkybox":true,"showFlares":true,"showImageEffects":true,"showParticleSystems":true,"showVisualEffectGraphs":true,"m_FxEnabled":true},"in2DMode":false,"pivot":{"x":-2.8575949668884279,"y":-0.6694257259368897,"z":1.5530097484588624},"rotation":{"x":-0.2701627314090729,"y":-0.3651134967803955,"z":0.11145004630088806,"w":-0.8841797709465027},"size":3.2959420680999758,"orthographic":false}